rasa_language/__init__.py
rasa_language/__main__.py
rasa_language/grammar.lark
rasa_language/parser.py
rasa_language/rasa_language.py
rasa_language-0.0.1.dist-info/entry_points.txt
rasa_language-0.0.1.dist-info/LICENSE
rasa_language-0.0.1.dist-info/WHEEL
rasa_language-0.0.1.dist-info/METADATA
rasa_language-0.0.1.dist-info/RECORD
